uds/__init__.py
uds/uds_communications/__init__.py
uds/uds_communications/TransportProtocols/TpFactory.py
uds/uds_communications/TransportProtocols/__init__.py
uds/uds_communications/TransportProtocols/config.ini
uds/uds_communications/TransportProtocols/iTp.py
uds/uds_communications/TransportProtocols/Can/CanConnection.py
uds/uds_communications/TransportProtocols/Can/CanConnectionFactory.py
uds/uds_communications/TransportProtocols/Can/CanTp.py
uds/uds_communications/TransportProtocols/Can/CanTpTypes.py
uds/uds_communications/TransportProtocols/Can/__init__.py
uds/uds_communications/TransportProtocols/Can/config.ini
uds/uds_communications/TransportProtocols/Lin/LinTp.py
uds/uds_communications/TransportProtocols/Lin/LinTpTypes.py
uds/uds_communications/TransportProtocols/Lin/__init__.py
uds/uds_communications/TransportProtocols/Lin/config.ini
uds/uds_communications/TransportProtocols/Test/TestTp.py
uds/uds_communications/TransportProtocols/Test/__init__.py
uds/uds_communications/Uds/Uds.py
uds/uds_communications/Uds/__init__.py
uds/uds_communications/Uds/config.ini
uds/uds_communications/Utilities/ResettableTimer.py
uds/uds_communications/Utilities/UtilityFunctions.py
uds/uds_communications/Utilities/__init__.py
uds/uds_communications/Utilities/iResettableTimer.py
uds/uds_config_tool/DecodeFunctions.py
uds/uds_config_tool/IHexFunctions.py
uds/uds_config_tool/UdsConfigTool.py
uds/uds_config_tool/UtilityFunctions.py
uds/uds_config_tool/__init__.py
uds/uds_config_tool/FunctionCreation/ClearDTCMethodFactory.py
uds/uds_config_tool/FunctionCreation/DiagnosticSessionControlMethodFactory.py
uds/uds_config_tool/FunctionCreation/ECUResetMethodFactory.py
uds/uds_config_tool/FunctionCreation/InputOutputControlMethodFactory.py
uds/uds_config_tool/FunctionCreation/ReadDTCMethodFactory.py
uds/uds_config_tool/FunctionCreation/ReadDataByIdentifierMethodFactory.py
uds/uds_config_tool/FunctionCreation/RequestDownloadMethodFactory.py
python_uds-1.0.2.dist-info/LICENSE.md
python_uds-1.0.2.dist-info/METADATA
python_uds-1.0.2.dist-info/WHEEL
python_uds-1.0.2.dist-info/top_level.txt
python_uds-1.0.2.dist-info/RECORD
